<nas_app_info>
	<nas_drive_preference_information>
		<version>1.0.8</version>
		<binary_url>https://p.buffalo.jp/buf-drv/hd/NASDrivePreference.zip</binary_url>
		<size>7843</size>
		<md5checksum>5cc37bd110767934ac3f8d316e5d5ed4</md5checksum>
	</nas_drive_preference_information>

	<nas_images_information>
		<version>1.0.0</version>
		<binary_url>https://p.buffalo.jp/buf-drv/hd/NASImages/1.0.0/</binary_url>
	</nas_images_information>

	<EIStrings_information>
		<version>1.0.2</version>
		<binary_url>https://p.buffalo.jp/buf-drv/hd/EIStrings.zip</binary_url>
		<size>41190</size>
		<md5checksum>ca35e94c7a11b3d75360ae8065b4cc75</md5checksum>
	</EIStrings_information>
</nas_app_info>